{"hazardous_domains": [], "ns": ["ns1.lvcs.net.", "ns2.lvcs.net.", "ns01.backupdns.com.", "ns02.backupdns.com."], "ipv4": ["107.191.43.242", "45.63.65.208", "207.246.85.154", "209.51.211.159", "50.62.49.74", "199.242.242.199", "199.242.242.198"], "ipv6": ["2001:19f0:5c00:92c3:5400:ff:fe19:fdd8", "2001:19f0:5:26f:5400:ff:fe43:785f"], "tld": ["net.", "gov.", "com."], "sld": ["lawrencecountyboe-ohio.gov.", "backupdns.com.", "lvcs.net."], "ps_ns": [], "ps_ipv4": [], "ps_ipv6": [], "ps_tld": [], "ps_sld": []}